climaker/__init__.py
climaker/action.py
climaker/parser.py
climaker/spec.py
climaker-0.1.0.dist-info/METADATA
climaker-0.1.0.dist-info/RECORD
climaker-0.1.0.dist-info/WHEEL
climaker-0.1.0.dist-info/top_level.txt
