Metadata-Version: 2.1
Name: climaker
Version: 0.1.0
Summary: Build a CLI parser with subcommands
Home-page: https://github.com/MrP4p3r/climaker
License: UNKNOWN
Platform: UNKNOWN
Classifier: Programming Language :: Python :: 3
Classifier: License :: OSI Approved :: MIT License
Classifier: Topic :: Software Development :: User Interfaces
Requires-Python: >=3.6.0
